MANIFEST.in
README.rst
ebtables.py
requirements.txt
setup.py
__pycache__/ebtables_c19823a81fcabf0305de42c5319650a0583eaa2d.c
ebtables.egg-info/PKG-INFO
ebtables.egg-info/SOURCES.txt
ebtables.egg-info/dependency_links.txt
ebtables.egg-info/not-zip-safe
ebtables.egg-info/requires.txt
ebtables.egg-info/top_level.txt
include/ebtables.h
include/ebtables_u.h
include/ethernetdb.h
include/linux/if_ether.h
include/linux/netfilter_bridge.h
include/linux/types.h
include/linux/netfilter_bridge/ebt_802_3.h
include/linux/netfilter_bridge/ebt_among.h
include/linux/netfilter_bridge/ebt_arp.h
include/linux/netfilter_bridge/ebt_arpreply.h
include/linux/netfilter_bridge/ebt_ip.h
include/linux/netfilter_bridge/ebt_ip6.h
include/linux/netfilter_bridge/ebt_limit.h
include/linux/netfilter_bridge/ebt_log.h
include/linux/netfilter_bridge/ebt_mark_m.h
include/linux/netfilter_bridge/ebt_mark_t.h
include/linux/netfilter_bridge/ebt_nat.h
include/linux/netfilter_bridge/ebt_nflog.h
include/linux/netfilter_bridge/ebt_pkttype.h
include/linux/netfilter_bridge/ebt_redirect.h
include/linux/netfilter_bridge/ebt_stp.h
include/linux/netfilter_bridge/ebt_ulog.h
include/linux/netfilter_bridge/ebt_vlan.h
include/linux/netfilter_bridge/ebtables.h