Metadata-Version: 1.0
Name: ebtables
Version: 0.2.0
Summary: Linux Ebtables bindings
Home-page: https://github.com/ldx/python-ebtables
Author: Vilmos Nebehaj
Author-email: v.nebehaj@gmail.com
License: UNKNOWN
Platform: UNKNOWN
